{
  "slug": "best-interactive-cat-toys",
  "title": "7 Best Interactive Cat Toys in 2026 (Tested & Reviewed)",
  "meta_description": "Looking for the best best interactive cat toys? We tested the top options so you don't have to. See our expert picks and save time. Check prices on Amazon.",
  "primary_keyword": "best interactive cat toys",
  "secondary_keywords": [],
  "word_count": 1654,
  "reading_time": "8 min",
  "category": "pets",
  "tags": [
    "best interactive cat toys",
    "pets"
  ],
  "angle": "listicle",
  "amazon_searches": [
    "best interactive cat toys",
    "best best interactive cat toys",
    "best interactive cat toys recommended"
  ],
  "status": "draft",
  "created_at": "2026-04-17T21:47:14.391735"
}